Metadata-Version: 1.0
Name: rehan-distributions
Version: 0.1
Summary: Gaussian and Binomial distributions
Home-page: UNKNOWN
Author: Rehan Ahmar Sk
Author-email: UNKNOWN
License: UNKNOWN
Platform: UNKNOWN
